{
	"name": "pl_single_activity_pg",
	"properties": {
		"activities": [
			{
				"name": "Execute Pipeline1",
				"type": "ExecutePipeline",
				"dependsOn": [],
				"userProperties": [],
				"typeProperties": {
					"pipeline": {
						"referenceName": "pl_empty_folder_if_exists",
						"type": "PipelineReference"
					},
					"waitOnCompletion": true,
					"parameters": {
						"p_building_type_name": {
							"value": "@pipeline().parameters.p_outer_building_type",
							"type": "Expression"
						}
					}
				}
			}
		],
		"parameters": {
			"p_outer_building_type": {
				"type": "string"
			}
		},
		"variables": {
			"v_rapidapi_key": {
				"type": "String"
			},
			"v_current_date": {
				"type": "String"
			}
		},
		"folder": {
			"name": "pg"
		},
		"annotations": []
	}
}